[
  {
    "valid": true,
    "options": [
      "DisallowUndefinedExtensions"
    ],
    "input": [
      {
        "@context": "dtmi:dtdl:context;4",
        "@id": "dtmi:example:sigma_yekk;1",
        "@type": "Interface",
        "schemas": {
          "@id": "dtmi:example:sigma_jogg;1",
          "@type": "Map",
          "mapKey": {
            "name": "sigma_flunn",
            "schema": "string"
          },
          "mapValue": {
            "name": "sigma_itch",
            "schema": "long"
          },
          "comment": "hello"
        }
      }
    ]
  },
  {
    "valid": true,
    "options": [
      "DisallowUndefinedExtensions"
    ],
    "input": [
      {
        "@context": "dtmi:dtdl:context;4",
        "@id": "dtmi:example:tau_beta;1",
        "@type": "Interface",
        "schemas": {
          "@id": "dtmi:example:sigma_vroo;1",
          "@type": "Map",
          "mapKey": {
            "name": "sigma_hi",
            "schema": "string"
          },
          "mapValue": {
            "name": "tau_alpha",
            "schema": "short"
          },
          "comment": [
            "hello"
          ]
        }
      }
    ]
  },
  {
    "valid": true,
    "options": [
      "DisallowUndefinedExtensions"
    ],
    "input": [
      {
        "@context": "dtmi:dtdl:context;4",
        "@id": "dtmi:example:tau_zeta;1",
        "@type": "Interface",
        "schemas": {
          "@id": "dtmi:example:tau_gamma;1",
          "@type": "Map",
          "mapKey": {
            "name": "tau_delta",
            "schema": "string"
          },
          "mapValue": {
            "name": "tau_epsilon",
            "schema": "string"
          },
          "comment": {
            "@value": "hello",
            "@type": "xsd:string"
          }
        }
      }
    ]
  },
  {
    "valid": true,
    "options": [
      "DisallowUndefinedExtensions"
    ],
    "input": [
      {
        "@context": "dtmi:dtdl:context;4",
        "@id": "dtmi:example:tau_kappa;1",
        "@type": "Interface",
        "schemas": {
          "@id": "dtmi:example:tau_eta;1",
          "@type": "Map",
          "mapKey": {
            "name": "tau_theta",
            "schema": "string"
          },
          "mapValue": {
            "name": "tau_iota",
            "schema": "time"
          },
          "comment": [
            {
              "@value": "hello",
              "@type": "xsd:string"
            }
          ]
        }
      }
    ]
  },
  {
    "valid": true,
    "options": [
      "DisallowUndefinedExtensions"
    ],
    "input": [
      {
        "@context": "dtmi:dtdl:context;4",
        "@id": "dtmi:example:tau_xi;1",
        "@type": "Interface",
        "schemas": {
          "@id": "dtmi:example:tau_lambda;1",
          "@type": "Map",
          "mapKey": {
            "name": "tau_mu",
            "schema": "string"
          },
          "mapValue": {
            "name": "tau_nu",
            "schema": "unsignedByte"
          },
          "comment": []
        }
      }
    ]
  },
  {
    "valid": false,
    "options": [
      "DisallowUndefinedExtensions"
    ],
    "input": [
      {
        "@context": "dtmi:dtdl:context;4",
        "@id": "dtmi:example:tau_sigma;1",
        "@type": "Interface",
        "schemas": {
          "@id": "dtmi:example:tau_omicron;1",
          "@type": "Map",
          "mapKey": {
            "name": "tau_pi",
            "schema": "string"
          },
          "mapValue": {
            "name": "tau_rho",
            "schema": "unsignedInteger"
          },
          "comment": null
        }
      }
    ]
  },
  {
    "valid": false,
    "options": [
      "AllowUndefinedExtensions"
    ],
    "input": [
      {
        "@context": "dtmi:dtdl:context;4",
        "@id": "dtmi:example:tau_chi;1",
        "@type": "Interface",
        "schemas": {
          "@context": "dtmi:undefinedExtension:context;1",
          "@id": "dtmi:example:tau_tau;1",
          "@type": "Map",
          "mapKey": {
            "name": "tau_upsilon",
            "schema": "string"
          },
          "mapValue": {
            "name": "tau_phi",
            "schema": "unsignedLong"
          },
          "comment": null
        }
      }
    ]
  },
  {
    "valid": false,
    "options": [
      "DisallowUndefinedExtensions"
    ],
    "input": [
      {
        "@context": "dtmi:dtdl:context;4",
        "@id": "dtmi:example:tau_wum;1",
        "@type": "Interface",
        "schemas": {
          "@id": "dtmi:example:tau_psi;1",
          "@type": "Map",
          "mapKey": {
            "name": "tau_omega",
            "schema": "string"
          },
          "mapValue": {
            "name": "tau_yuzz",
            "schema": "unsignedShort"
          },
          "comment": true
        }
      }
    ]
  },
  {
    "valid": false,
    "options": [
      "AllowUndefinedExtensions"
    ],
    "input": [
      {
        "@context": "dtmi:dtdl:context;4",
        "@id": "dtmi:example:tau_glikk;1",
        "@type": "Interface",
        "schemas": {
          "@context": "dtmi:undefinedExtension:context;1",
          "@id": "dtmi:example:tau_um;1",
          "@type": "Map",
          "mapKey": {
            "name": "tau_humpf",
            "schema": "string"
          },
          "mapValue": {
            "name": "tau_fuddle",
            "schema": "uuid"
          },
          "comment": true
        }
      }
    ]
  },
  {
    "valid": false,
    "options": [
      "DisallowUndefinedExtensions"
    ],
    "input": [
      {
        "@context": "dtmi:dtdl:context;4",
        "@id": "dtmi:example:tau_thnad;1",
        "@type": "Interface",
        "schemas": {
          "@id": "dtmi:example:tau_nuh;1",
          "@type": "Map",
          "mapKey": {
            "name": "tau_snee",
            "schema": "string"
          },
          "mapValue": {
            "name": "tau_quan",
            "schema": "boolean"
          },
          "comment": 626
        }
      }
    ]
  },
  {
    "valid": false,
    "options": [
      "AllowUndefinedExtensions"
    ],
    "input": [
      {
        "@context": "dtmi:dtdl:context;4",
        "@id": "dtmi:example:tau_jogg;1",
        "@type": "Interface",
        "schemas": {
          "@context": "dtmi:undefinedExtension:context;1",
          "@id": "dtmi:example:tau_spazz;1",
          "@type": "Map",
          "mapKey": {
            "name": "tau_floob",
            "schema": "string"
          },
          "mapValue": {
            "name": "tau_zatz",
            "schema": "byte"
          },
          "comment": 626
        }
      }
    ]
  },
  {
    "valid": false,
    "options": [
      "DisallowUndefinedExtensions"
    ],
    "input": [
      {
        "@context": "dtmi:dtdl:context;4",
        "@id": "dtmi:example:tau_vroo;1",
        "@type": "Interface",
        "schemas": {
          "@id": "dtmi:example:tau_flunn;1",
          "@type": "Map",
          "mapKey": {
            "name": "tau_itch",
            "schema": "string"
          },
          "mapValue": {
            "name": "tau_yekk",
            "schema": "bytes"
          },
          "comment": [
            null
          ]
        }
      }
    ]
  },
  {
    "valid": false,
    "options": [
      "AllowUndefinedExtensions"
    ],
    "input": [
      {
        "@context": "dtmi:dtdl:context;4",
        "@id": "dtmi:example:upsilon_gamma;1",
        "@type": "Interface",
        "schemas": {
          "@context": "dtmi:undefinedExtension:context;1",
          "@id": "dtmi:example:tau_hi;1",
          "@type": "Map",
          "mapKey": {
            "name": "upsilon_alpha",
            "schema": "string"
          },
          "mapValue": {
            "name": "upsilon_beta",
            "schema": "date"
          },
          "comment": [
            null
          ]
        }
      }
    ]
  },
  {
    "valid": false,
    "options": [
      "DisallowUndefinedExtensions"
    ],
    "input": [
      {
        "@context": "dtmi:dtdl:context;4",
        "@id": "dtmi:example:upsilon_eta;1",
        "@type": "Interface",
        "schemas": {
          "@id": "dtmi:example:upsilon_delta;1",
          "@type": "Map",
          "mapKey": {
            "name": "upsilon_epsilon",
            "schema": "string"
          },
          "mapValue": {
            "name": "upsilon_zeta",
            "schema": "dateTime"
          },
          "comment": [
            true
          ]
        }
      }
    ]
  },
  {
    "valid": false,
    "options": [
      "AllowUndefinedExtensions"
    ],
    "input": [
      {
        "@context": "dtmi:dtdl:context;4",
        "@id": "dtmi:example:upsilon_lambda;1",
        "@type": "Interface",
        "schemas": {
          "@context": "dtmi:undefinedExtension:context;1",
          "@id": "dtmi:example:upsilon_theta;1",
          "@type": "Map",
          "mapKey": {
            "name": "upsilon_iota",
            "schema": "string"
          },
          "mapValue": {
            "name": "upsilon_kappa",
            "schema": "decimal"
          },
          "comment": [
            true
          ]
        }
      }
    ]
  },
  {
    "valid": false,
    "options": [
      "DisallowUndefinedExtensions"
    ],
    "input": [
      {
        "@context": "dtmi:dtdl:context;4",
        "@id": "dtmi:example:upsilon_omicron;1",
        "@type": "Interface",
        "schemas": {
          "@id": "dtmi:example:upsilon_mu;1",
          "@type": "Map",
          "mapKey": {
            "name": "upsilon_nu",
            "schema": "string"
          },
          "mapValue": {
            "name": "upsilon_xi",
            "schema": "double"
          },
          "comment": [
            626
          ]
        }
      }
    ]
  },
  {
    "valid": false,
    "options": [
      "AllowUndefinedExtensions"
    ],
    "input": [
      {
        "@context": "dtmi:dtdl:context;4",
        "@id": "dtmi:example:upsilon_tau;1",
        "@type": "Interface",
        "schemas": {
          "@context": "dtmi:undefinedExtension:context;1",
          "@id": "dtmi:example:upsilon_pi;1",
          "@type": "Map",
          "mapKey": {
            "name": "upsilon_rho",
            "schema": "string"
          },
          "mapValue": {
            "name": "upsilon_sigma",
            "schema": "duration"
          },
          "comment": [
            626
          ]
        }
      }
    ]
  },
  {
    "valid": false,
    "options": [
      "DisallowUndefinedExtensions"
    ],
    "input": [
      {
        "@context": "dtmi:dtdl:context;4",
        "@id": "dtmi:example:upsilon_psi;1",
        "@type": "Interface",
        "schemas": {
          "@id": "dtmi:example:upsilon_upsilon;1",
          "@type": "Map",
          "mapKey": {
            "name": "upsilon_phi",
            "schema": "string"
          },
          "mapValue": {
            "name": "upsilon_chi",
            "schema": "float"
          },
          "comment": {}
        }
      }
    ]
  },
  {
    "valid": false,
    "options": [
      "AllowUndefinedExtensions"
    ],
    "input": [
      {
        "@context": "dtmi:dtdl:context;4",
        "@id": "dtmi:example:upsilon_um;1",
        "@type": "Interface",
        "schemas": {
          "@context": "dtmi:undefinedExtension:context;1",
          "@id": "dtmi:example:upsilon_omega;1",
          "@type": "Map",
          "mapKey": {
            "name": "upsilon_yuzz",
            "schema": "string"
          },
          "mapValue": {
            "name": "upsilon_wum",
            "schema": "integer"
          },
          "comment": {}
        }
      }
    ]
  },
  {
    "valid": false,
    "options": [
      "DisallowUndefinedExtensions"
    ],
    "input": [
      {
        "@context": "dtmi:dtdl:context;4",
        "@id": "dtmi:example:upsilon_nuh;1",
        "@type": "Interface",
        "schemas": {
          "@id": "dtmi:example:upsilon_humpf;1",
          "@type": "Map",
          "mapKey": {
            "name": "upsilon_fuddle",
            "schema": "string"
          },
          "mapValue": {
            "name": "upsilon_glikk",
            "schema": "long"
          },
          "comment": [
            {}
          ]
        }
      }
    ]
  },
  {
    "valid": false,
    "options": [
      "AllowUndefinedExtensions"
    ],
    "input": [
      {
        "@context": "dtmi:dtdl:context;4",
        "@id": "dtmi:example:upsilon_spazz;1",
        "@type": "Interface",
        "schemas": {
          "@context": "dtmi:undefinedExtension:context;1",
          "@id": "dtmi:example:upsilon_snee;1",
          "@type": "Map",
          "mapKey": {
            "name": "upsilon_quan",
            "schema": "string"
          },
          "mapValue": {
            "name": "upsilon_thnad",
            "schema": "short"
          },
          "comment": [
            {}
          ]
        }
      }
    ]
  }
]
