[
  {
    "valid": true,
    "options": [
      "DisallowUndefinedExtensions"
    ],
    "input": [
      {
        "@context": "dtmi:dtdl:context;4",
        "@id": "dtmi:example:hi_psi;1",
        "@type": "Interface",
        "extends": {
          "@id": "dtmi:example:hi_chi;1",
          "@type": "Interface",
          "contents": {
            "@type": "Telemetry",
            "name": "hi_phi",
            "schema": {
              "@type": "Array",
              "elementSchema": "unsignedByte"
            }
          }
        }
      }
    ]
  },
  {
    "valid": true,
    "options": [
      "DisallowUndefinedExtensions"
    ],
    "input": [
      {
        "@context": "dtmi:dtdl:context;4",
        "@id": "dtmi:example:hi_wum;1",
        "@type": "Interface",
        "extends": {
          "@id": "dtmi:example:hi_yuzz;1",
          "@type": "Interface",
          "contents": {
            "@type": "Telemetry",
            "name": "hi_omega",
            "schema": [
              {
                "@type": "Array",
                "elementSchema": "unsignedInteger"
              }
            ]
          }
        }
      }
    ]
  },
  {
    "valid": true,
    "options": [
      "DisallowUndefinedExtensions"
    ],
    "input": [
      {
        "@context": "dtmi:dtdl:context;4",
        "@id": "dtmi:example:hi_um;1",
        "@type": "Interface",
        "schemas": {
          "@id": "dtmi:ex:dependentRef;1",
          "@type": "Array",
          "elementSchema": "unsignedLong"
        },
        "contents": {
          "@type": "Telemetry",
          "name": "hi_humpf",
          "schema": "dtmi:ex:dependentRef;1"
        }
      }
    ]
  },
  {
    "valid": true,
    "options": [
      "DisallowUndefinedExtensions"
    ],
    "input": [
      {
        "@context": "dtmi:dtdl:context;4",
        "@id": "dtmi:example:hi_fuddle;1",
        "@type": "Interface",
        "schemas": {
          "@id": "dtmi:ex:dependentRef;1",
          "@type": "Array",
          "elementSchema": "unsignedShort"
        },
        "contents": {
          "@type": "Telemetry",
          "name": "hi_glikk",
          "schema": [
            "dtmi:ex:dependentRef;1"
          ]
        }
      }
    ]
  },
  {
    "valid": true,
    "options": [
      "DisallowUndefinedExtensions"
    ],
    "input": [
      {
        "@context": "dtmi:dtdl:context;4",
        "@id": "dtmi:example:hi_thnad;1",
        "@type": "Interface",
        "extends": {
          "@id": "dtmi:example:hi_quan;1",
          "@type": "Interface",
          "contents": {
            "@type": "Telemetry",
            "name": "hi_snee",
            "schema": {
              "@id": "dtmi:example:hi_nuh;1",
              "@type": "Array",
              "elementSchema": "boolean",
              "@context": "dtmi:dtdl:context;2"
            }
          }
        }
      }
    ]
  },
  {
    "valid": true,
    "options": [
      "DisallowUndefinedExtensions"
    ],
    "input": [
      {
        "@context": "dtmi:dtdl:context;4",
        "@id": "dtmi:example:hi_jogg;1",
        "@type": "Interface",
        "extends": {
          "@id": "dtmi:example:hi_zatz;1",
          "@type": "Interface",
          "contents": {
            "@type": "Telemetry",
            "name": "hi_floob",
            "schema": {
              "@id": "dtmi:example:hi_spazz;1",
              "@type": "Array",
              "elementSchema": "date",
              "@context": "dtmi:dtdl:context;3"
            }
          }
        }
      }
    ]
  },
  {
    "valid": false,
    "options": [
      "DisallowUndefinedExtensions"
    ],
    "input": [
      {
        "@context": "dtmi:dtdl:context;4",
        "@id": "dtmi:example:hi_flunn;1",
        "@type": "Interface",
        "schemas": {
          "@id": "dtmi:ex:dependentRef;1",
          "@type": "Array",
          "elementSchema": "bytes"
        },
        "contents": {
          "@type": "Telemetry",
          "name": "hi_itch",
          "schema": [
            {
              "@type": "Array",
              "elementSchema": "byte"
            },
            "dtmi:ex:dependentRef;1"
          ]
        }
      }
    ]
  },
  {
    "valid": false,
    "options": [
      "AllowUndefinedExtensions"
    ],
    "input": [
      {
        "@context": "dtmi:dtdl:context;4",
        "@id": "dtmi:example:hi_yekk;1",
        "@type": "Interface",
        "schemas": {
          "@id": "dtmi:ex:dependentRef;1",
          "@type": "Array",
          "elementSchema": "dateTime"
        },
        "contents": {
          "@context": "dtmi:undefinedExtension:context;1",
          "@type": "Telemetry",
          "name": "hi_vroo",
          "schema": [
            {
              "@type": "Array",
              "elementSchema": "date"
            },
            "dtmi:ex:dependentRef;1"
          ]
        }
      }
    ]
  },
  {
    "valid": true,
    "options": [
      "DisallowUndefinedExtensions"
    ],
    "input": [
      {
        "@context": "dtmi:dtdl:context;4",
        "@id": "dtmi:example:alpha_alpha;1",
        "@type": "Interface",
        "contents": {
          "@type": "Telemetry",
          "name": "hi_hi",
          "schema": "string"
        }
      }
    ]
  },
  {
    "valid": true,
    "options": [
      "DisallowUndefinedExtensions"
    ],
    "input": [
      {
        "@context": "dtmi:dtdl:context;4",
        "@id": "dtmi:example:alpha_gamma;1",
        "@type": "Interface",
        "contents": {
          "@type": "Telemetry",
          "name": "alpha_beta",
          "schema": [
            "string"
          ]
        }
      }
    ]
  },
  {
    "valid": true,
    "options": [
      "DisallowUndefinedExtensions"
    ],
    "input": [
      {
        "@context": "dtmi:dtdl:context;4",
        "@id": "dtmi:example:alpha_epsilon;1",
        "@type": "Interface",
        "contents": {
          "@type": "Telemetry",
          "name": "alpha_delta",
          "schema": "dtmi:dtdl:instance:Schema:string;4"
        }
      }
    ]
  },
  {
    "valid": true,
    "options": [
      "DisallowUndefinedExtensions"
    ],
    "input": [
      {
        "@context": "dtmi:dtdl:context;4",
        "@id": "dtmi:example:alpha_eta;1",
        "@type": "Interface",
        "contents": {
          "@type": "Telemetry",
          "name": "alpha_zeta",
          "schema": [
            "dtmi:dtdl:instance:Schema:string;4"
          ]
        }
      }
    ]
  },
  {
    "valid": true,
    "options": [
      "DisallowUndefinedExtensions"
    ],
    "input": [
      {
        "@context": "dtmi:dtdl:context;4",
        "@id": "dtmi:example:alpha_iota;1",
        "@type": "Interface",
        "contents": {
          "@type": "Telemetry",
          "name": "alpha_theta",
          "schema": "point"
        }
      }
    ]
  },
  {
    "valid": true,
    "options": [
      "DisallowUndefinedExtensions"
    ],
    "input": [
      {
        "@context": "dtmi:dtdl:context;4",
        "@id": "dtmi:example:alpha_lambda;1",
        "@type": "Interface",
        "contents": {
          "@type": "Telemetry",
          "name": "alpha_kappa",
          "schema": [
            "point"
          ]
        }
      }
    ]
  },
  {
    "valid": true,
    "options": [
      "DisallowUndefinedExtensions"
    ],
    "input": [
      {
        "@context": "dtmi:dtdl:context;4",
        "@id": "dtmi:example:alpha_nu;1",
        "@type": "Interface",
        "contents": {
          "@type": "Telemetry",
          "name": "alpha_mu",
          "schema": "dtmi:standard:schema:geospatial:point;4"
        }
      }
    ]
  },
  {
    "valid": true,
    "options": [
      "DisallowUndefinedExtensions"
    ],
    "input": [
      {
        "@context": "dtmi:dtdl:context;4",
        "@id": "dtmi:example:alpha_omicron;1",
        "@type": "Interface",
        "contents": {
          "@type": "Telemetry",
          "name": "alpha_xi",
          "schema": [
            "dtmi:standard:schema:geospatial:point;4"
          ]
        }
      }
    ]
  },
  {
    "valid": false,
    "options": [
      "DisallowUndefinedExtensions"
    ],
    "input": [
      {
        "@context": "dtmi:dtdl:context;4",
        "@id": "dtmi:example:alpha_rho;1",
        "@type": "Interface",
        "contents": {
          "@type": "Telemetry",
          "name": "alpha_pi",
          "schema": "Foobar"
        }
      }
    ]
  },
  {
    "valid": false,
    "options": [
      "AllowUndefinedExtensions"
    ],
    "input": [
      {
        "@context": "dtmi:dtdl:context;4",
        "@id": "dtmi:example:alpha_tau;1",
        "@type": "Interface",
        "contents": {
          "@context": "dtmi:undefinedExtension:context;1",
          "@type": "Telemetry",
          "name": "alpha_sigma",
          "schema": "Foobar"
        }
      }
    ]
  },
  {
    "valid": false,
    "options": [
      "DisallowUndefinedExtensions"
    ],
    "input": [
      {
        "@context": "dtmi:dtdl:context;4",
        "@id": "dtmi:example:alpha_phi;1",
        "@type": "Interface",
        "contents": {
          "@type": "Telemetry",
          "name": "alpha_upsilon",
          "schema": null
        }
      }
    ]
  },
  {
    "valid": false,
    "options": [
      "AllowUndefinedExtensions"
    ],
    "input": [
      {
        "@context": "dtmi:dtdl:context;4",
        "@id": "dtmi:example:alpha_psi;1",
        "@type": "Interface",
        "contents": {
          "@context": "dtmi:undefinedExtension:context;1",
          "@type": "Telemetry",
          "name": "alpha_chi",
          "schema": null
        }
      }
    ]
  },
  {
    "valid": false,
    "options": [
      "DisallowUndefinedExtensions"
    ],
    "input": [
      {
        "@context": "dtmi:dtdl:context;4",
        "@id": "dtmi:example:alpha_yuzz;1",
        "@type": "Interface",
        "contents": {
          "@type": "Telemetry",
          "name": "alpha_omega",
          "schema": true
        }
      }
    ]
  },
  {
    "valid": false,
    "options": [
      "AllowUndefinedExtensions"
    ],
    "input": [
      {
        "@context": "dtmi:dtdl:context;4",
        "@id": "dtmi:example:alpha_um;1",
        "@type": "Interface",
        "contents": {
          "@context": "dtmi:undefinedExtension:context;1",
          "@type": "Telemetry",
          "name": "alpha_wum",
          "schema": true
        }
      }
    ]
  },
  {
    "valid": false,
    "options": [
      "DisallowUndefinedExtensions"
    ],
    "input": [
      {
        "@context": "dtmi:dtdl:context;4",
        "@id": "dtmi:example:alpha_fuddle;1",
        "@type": "Interface",
        "contents": {
          "@type": "Telemetry",
          "name": "alpha_humpf",
          "schema": 626
        }
      }
    ]
  },
  {
    "valid": false,
    "options": [
      "AllowUndefinedExtensions"
    ],
    "input": [
      {
        "@context": "dtmi:dtdl:context;4",
        "@id": "dtmi:example:alpha_nuh;1",
        "@type": "Interface",
        "contents": {
          "@context": "dtmi:undefinedExtension:context;1",
          "@type": "Telemetry",
          "name": "alpha_glikk",
          "schema": 626
        }
      }
    ]
  },
  {
    "valid": false,
    "options": [
      "DisallowUndefinedExtensions"
    ],
    "input": [
      {
        "@context": "dtmi:dtdl:context;4",
        "@id": "dtmi:example:alpha_quan;1",
        "@type": "Interface",
        "contents": {
          "@type": "Telemetry",
          "name": "alpha_snee",
          "schema": [
            null
          ]
        }
      }
    ]
  },
  {
    "valid": false,
    "options": [
      "AllowUndefinedExtensions"
    ],
    "input": [
      {
        "@context": "dtmi:dtdl:context;4",
        "@id": "dtmi:example:alpha_spazz;1",
        "@type": "Interface",
        "contents": {
          "@context": "dtmi:undefinedExtension:context;1",
          "@type": "Telemetry",
          "name": "alpha_thnad",
          "schema": [
            null
          ]
        }
      }
    ]
  },
  {
    "valid": false,
    "options": [
      "DisallowUndefinedExtensions"
    ],
    "input": [
      {
        "@context": "dtmi:dtdl:context;4",
        "@id": "dtmi:example:alpha_zatz;1",
        "@type": "Interface",
        "contents": {
          "@type": "Telemetry",
          "name": "alpha_floob",
          "schema": [
            true
          ]
        }
      }
    ]
  },
  {
    "valid": false,
    "options": [
      "AllowUndefinedExtensions"
    ],
    "input": [
      {
        "@context": "dtmi:dtdl:context;4",
        "@id": "dtmi:example:alpha_flunn;1",
        "@type": "Interface",
        "contents": {
          "@context": "dtmi:undefinedExtension:context;1",
          "@type": "Telemetry",
          "name": "alpha_jogg",
          "schema": [
            true
          ]
        }
      }
    ]
  },
  {
    "valid": false,
    "options": [
      "DisallowUndefinedExtensions"
    ],
    "input": [
      {
        "@context": "dtmi:dtdl:context;4",
        "@id": "dtmi:example:alpha_yekk;1",
        "@type": "Interface",
        "contents": {
          "@type": "Telemetry",
          "name": "alpha_itch",
          "schema": [
            626
          ]
        }
      }
    ]
  },
  {
    "valid": false,
    "options": [
      "AllowUndefinedExtensions"
    ],
    "input": [
      {
        "@context": "dtmi:dtdl:context;4",
        "@id": "dtmi:example:alpha_hi;1",
        "@type": "Interface",
        "contents": {
          "@context": "dtmi:undefinedExtension:context;1",
          "@type": "Telemetry",
          "name": "alpha_vroo",
          "schema": [
            626
          ]
        }
      }
    ]
  },
  {
    "valid": false,
    "options": [
      "DisallowUndefinedExtensions"
    ],
    "input": [
      {
        "@context": "dtmi:dtdl:context;4",
        "@id": "dtmi:example:beta_beta;1",
        "@type": "Interface",
        "contents": {
          "@type": "Telemetry",
          "name": "beta_alpha",
          "schema": {}
        }
      }
    ]
  },
  {
    "valid": false,
    "options": [
      "AllowUndefinedExtensions"
    ],
    "input": [
      {
        "@context": "dtmi:dtdl:context;4",
        "@id": "dtmi:example:beta_delta;1",
        "@type": "Interface",
        "contents": {
          "@context": "dtmi:undefinedExtension:context;1",
          "@type": "Telemetry",
          "name": "beta_gamma",
          "schema": {}
        }
      }
    ]
  },
  {
    "valid": false,
    "options": [
      "DisallowUndefinedExtensions"
    ],
    "input": [
      {
        "@context": "dtmi:dtdl:context;4",
        "@id": "dtmi:example:beta_zeta;1",
        "@type": "Interface",
        "contents": {
          "@type": "Telemetry",
          "name": "beta_epsilon",
          "schema": [
            {}
          ]
        }
      }
    ]
  },
  {
    "valid": false,
    "options": [
      "AllowUndefinedExtensions"
    ],
    "input": [
      {
        "@context": "dtmi:dtdl:context;4",
        "@id": "dtmi:example:beta_theta;1",
        "@type": "Interface",
        "contents": {
          "@context": "dtmi:undefinedExtension:context;1",
          "@type": "Telemetry",
          "name": "beta_eta",
          "schema": [
            {}
          ]
        }
      }
    ]
  },
  {
    "valid": false,
    "options": [
      "DisallowUndefinedExtensions"
    ],
    "input": [
      {
        "@context": "dtmi:dtdl:context;4",
        "@id": "dtmi:example:beta_kappa;1",
        "@type": "Interface",
        "contents": {
          "@type": "Telemetry",
          "name": "beta_iota",
          "schema": []
        }
      }
    ]
  },
  {
    "valid": false,
    "options": [
      "AllowUndefinedExtensions"
    ],
    "input": [
      {
        "@context": "dtmi:dtdl:context;4",
        "@id": "dtmi:example:beta_mu;1",
        "@type": "Interface",
        "contents": {
          "@context": "dtmi:undefinedExtension:context;1",
          "@type": "Telemetry",
          "name": "beta_lambda",
          "schema": []
        }
      }
    ]
  }
]
