[
  {
    "valid": true,
    "desirable": false,
    "options": [
      "DisallowUndefinedExtensions"
    ],
    "input": [
      {
        "@context": "dtmi:dtdl:context;3",
        "@id": "dtmi:example:jogg_sigma;1",
        "@type": "Interface",
        "schemas": {
          "@id": "dtmi:example:jogg_pi;1",
          "@type": "Map",
          "mapValue": {
            "name": "jogg_rho",
            "schema": "boolean"
          },
          "mapKey": {
            "name": "jogg_omicron",
            "schema": "string",
            "@type": [
              "MapKey",
              "dtmi:dtdl:class:MapKey;3"
            ]
          }
        }
      }
    ]
  }
]
