[
  {
    "valid": true,
    "options": [
      "DisallowUndefinedExtensions"
    ],
    "input": [
      {
        "@context": "dtmi:dtdl:context;3",
        "@id": "dtmi:example:humpf_gamma;1",
        "@type": "Interface",
        "contents": {
          "@type": "Property",
          "name": "humpf_beta",
          "schema": {
            "@type": "Map",
            "mapKey": {
              "name": "humpf_alpha",
              "schema": "string"
            },
            "mapValue": {
              "name": "um_hi",
              "schema": "string",
              "@context": "dtmi:dtdl:extension:quantitativeTypes;1"
            }
          }
        }
      }
    ]
  },
  {
    "valid": true,
    "options": [
      "DisallowUndefinedExtensions"
    ],
    "input": [
      {
        "@context": "dtmi:dtdl:context;3",
        "@id": "dtmi:example:humpf_eta;1",
        "@type": "Interface",
        "contents": {
          "@type": "Property",
          "name": "humpf_zeta",
          "schema": {
            "@type": "Map",
            "mapKey": {
              "name": "humpf_epsilon",
              "schema": "string"
            },
            "mapValue": {
              "name": "humpf_delta",
              "schema": "time",
              "@context": []
            }
          }
        }
      }
    ]
  },
  {
    "valid": true,
    "options": [
      "DisallowUndefinedExtensions"
    ],
    "input": [
      {
        "@context": "dtmi:dtdl:context;3",
        "@id": "dtmi:example:humpf_lambda;1",
        "@type": "Interface",
        "contents": {
          "@type": "Property",
          "name": "humpf_kappa",
          "schema": {
            "@type": "Map",
            "mapKey": {
              "name": "humpf_iota",
              "schema": "string"
            },
            "mapValue": {
              "name": "humpf_theta",
              "schema": "boolean",
              "@context": [
                "dtmi:dtdl:extension:quantitativeTypes;1"
              ]
            }
          }
        }
      }
    ]
  },
  {
    "valid": false,
    "options": [
      "DisallowUndefinedExtensions"
    ],
    "input": [
      {
        "@context": "dtmi:dtdl:context;3",
        "@id": "dtmi:example:humpf_omicron;1",
        "@type": "Interface",
        "contents": {
          "@type": "Property",
          "name": "humpf_xi",
          "schema": {
            "@type": "Map",
            "mapKey": {
              "name": "humpf_nu",
              "schema": "string"
            },
            "mapValue": {
              "name": "humpf_mu",
              "schema": "date",
              "@context": null
            }
          }
        }
      }
    ]
  },
  {
    "valid": false,
    "options": [
      "DisallowUndefinedExtensions"
    ],
    "input": [
      {
        "@context": "dtmi:dtdl:context;3",
        "@id": "dtmi:example:humpf_tau;1",
        "@type": "Interface",
        "contents": {
          "@type": "Property",
          "name": "humpf_sigma",
          "schema": {
            "@type": "Map",
            "mapKey": {
              "name": "humpf_rho",
              "schema": "string"
            },
            "mapValue": {
              "name": "humpf_pi",
              "schema": "dateTime",
              "@context": 626
            }
          }
        }
      }
    ]
  },
  {
    "valid": false,
    "options": [
      "DisallowUndefinedExtensions"
    ],
    "input": [
      {
        "@context": "dtmi:dtdl:context;3",
        "@id": "dtmi:example:humpf_psi;1",
        "@type": "Interface",
        "contents": {
          "@type": "Property",
          "name": "humpf_chi",
          "schema": {
            "@type": "Map",
            "mapKey": {
              "name": "humpf_phi",
              "schema": "string"
            },
            "mapValue": {
              "name": "humpf_upsilon",
              "schema": "double",
              "@context": true
            }
          }
        }
      }
    ]
  },
  {
    "valid": false,
    "options": [
      "DisallowUndefinedExtensions"
    ],
    "input": [
      {
        "@context": "dtmi:dtdl:context;3",
        "@id": "dtmi:example:humpf_um;1",
        "@type": "Interface",
        "contents": {
          "@type": "Property",
          "name": "humpf_wum",
          "schema": {
            "@type": "Map",
            "mapKey": {
              "name": "humpf_yuzz",
              "schema": "string"
            },
            "mapValue": {
              "name": "humpf_omega",
              "schema": "duration",
              "@context": [
                null
              ]
            }
          }
        }
      }
    ]
  },
  {
    "valid": false,
    "options": [
      "DisallowUndefinedExtensions"
    ],
    "input": [
      {
        "@context": "dtmi:dtdl:context;3",
        "@id": "dtmi:example:humpf_nuh;1",
        "@type": "Interface",
        "contents": {
          "@type": "Property",
          "name": "humpf_glikk",
          "schema": {
            "@type": "Map",
            "mapKey": {
              "name": "humpf_fuddle",
              "schema": "string"
            },
            "mapValue": {
              "name": "humpf_humpf",
              "schema": "float",
              "@context": [
                626
              ]
            }
          }
        }
      }
    ]
  },
  {
    "valid": false,
    "options": [
      "DisallowUndefinedExtensions"
    ],
    "input": [
      {
        "@context": "dtmi:dtdl:context;3",
        "@id": "dtmi:example:humpf_spazz;1",
        "@type": "Interface",
        "contents": {
          "@type": "Property",
          "name": "humpf_thnad",
          "schema": {
            "@type": "Map",
            "mapKey": {
              "name": "humpf_quan",
              "schema": "string"
            },
            "mapValue": {
              "name": "humpf_snee",
              "schema": "integer",
              "@context": [
                true
              ]
            }
          }
        }
      }
    ]
  },
  {
    "valid": false,
    "options": [
      "DisallowUndefinedExtensions"
    ],
    "input": [
      {
        "@context": "dtmi:dtdl:context;3",
        "@id": "dtmi:example:humpf_flunn;1",
        "@type": "Interface",
        "contents": {
          "@type": "Property",
          "name": "humpf_jogg",
          "schema": {
            "@type": "Map",
            "mapKey": {
              "name": "humpf_zatz",
              "schema": "string"
            },
            "mapValue": {
              "name": "humpf_floob",
              "schema": "long",
              "@context": "dtmi:dtdl:extension:quantitativeTypes"
            }
          }
        }
      }
    ]
  },
  {
    "valid": false,
    "options": [
      "DisallowUndefinedExtensions"
    ],
    "input": [
      {
        "@context": "dtmi:dtdl:context;3",
        "@id": "dtmi:example:humpf_hi;1",
        "@type": "Interface",
        "contents": {
          "@type": "Property",
          "name": "humpf_vroo",
          "schema": {
            "@type": "Map",
            "mapKey": {
              "name": "humpf_yekk",
              "schema": "string"
            },
            "mapValue": {
              "name": "humpf_itch",
              "schema": "string",
              "@context": "http://dtdl/extension/quantitativeTypes/1"
            }
          }
        }
      }
    ]
  },
  {
    "valid": false,
    "options": [
      "DisallowUndefinedExtensions"
    ],
    "input": [
      {
        "@context": "dtmi:dtdl:context;3",
        "@id": "dtmi:example:fuddle_delta;1",
        "@type": "Interface",
        "contents": {
          "@type": "Property",
          "name": "fuddle_gamma",
          "schema": {
            "@type": "Map",
            "mapKey": {
              "name": "fuddle_beta",
              "schema": "string"
            },
            "mapValue": {
              "name": "fuddle_alpha",
              "schema": "time",
              "@context": "quantitativeTypes;1"
            }
          }
        }
      }
    ]
  },
  {
    "valid": false,
    "options": [
      "DisallowUndefinedExtensions"
    ],
    "input": [
      {
        "@context": "dtmi:dtdl:context;3",
        "@id": "dtmi:example:fuddle_theta;1",
        "@type": "Interface",
        "contents": {
          "@type": "Property",
          "name": "fuddle_eta",
          "schema": {
            "@type": "Map",
            "mapKey": {
              "name": "fuddle_zeta",
              "schema": "string"
            },
            "mapValue": {
              "name": "fuddle_epsilon",
              "schema": "boolean",
              "@context": {}
            }
          }
        }
      }
    ]
  },
  {
    "valid": false,
    "options": [
      "DisallowUndefinedExtensions"
    ],
    "input": [
      {
        "@context": "dtmi:dtdl:context;3",
        "@id": "dtmi:example:fuddle_mu;1",
        "@type": "Interface",
        "contents": {
          "@type": "Property",
          "name": "fuddle_lambda",
          "schema": {
            "@type": "Map",
            "mapKey": {
              "name": "fuddle_kappa",
              "schema": "string"
            },
            "mapValue": {
              "name": "fuddle_iota",
              "schema": "date",
              "@context": {
                "foo": "dtmi:foo:bar;1"
              }
            }
          }
        }
      }
    ]
  },
  {
    "valid": false,
    "options": [
      "DisallowUndefinedExtensions"
    ],
    "input": [
      {
        "@context": "dtmi:dtdl:context;3",
        "@id": "dtmi:example:fuddle_pi;1",
        "@type": "Interface",
        "contents": {
          "@type": "Property",
          "name": "fuddle_omicron",
          "schema": {
            "@type": "Map",
            "mapKey": {
              "name": "fuddle_xi",
              "schema": "string"
            },
            "mapValue": {
              "name": "fuddle_nu",
              "schema": "dateTime",
              "@context": [
                {}
              ]
            }
          }
        }
      }
    ]
  },
  {
    "valid": false,
    "options": [
      "DisallowUndefinedExtensions"
    ],
    "input": [
      {
        "@context": "dtmi:dtdl:context;3",
        "@id": "dtmi:example:fuddle_upsilon;1",
        "@type": "Interface",
        "contents": {
          "@type": "Property",
          "name": "fuddle_tau",
          "schema": {
            "@type": "Map",
            "mapKey": {
              "name": "fuddle_sigma",
              "schema": "string"
            },
            "mapValue": {
              "name": "fuddle_rho",
              "schema": "double",
              "@context": [
                {
                  "foo": "dtmi:foo:bar;1"
                }
              ]
            }
          }
        }
      }
    ]
  }
]
