[
  {
    "valid": true,
    "options": [
      "DisallowUndefinedExtensions"
    ],
    "input": [
      {
        "@context": "dtmi:dtdl:context;3",
        "@id": "dtmi:example:zatz_eta;1",
        "@type": "Interface",
        "schemas": {
          "@id": "dtmi:foo:bar;7",
          "@type": "Enum",
          "valueSchema": "integer"
        }
      }
    ]
  },
  {
    "valid": true,
    "options": [
      "DisallowUndefinedExtensions"
    ],
    "input": [
      {
        "@context": "dtmi:dtdl:context;3",
        "@id": "dtmi:example:zatz_theta;1",
        "@type": "Interface",
        "schemas": {
          "@id": "dtmi:foo:bar;108675309",
          "@type": "Enum",
          "valueSchema": "integer"
        }
      }
    ]
  },
  {
    "valid": true,
    "options": [
      "DisallowUndefinedExtensions"
    ],
    "input": [
      {
        "@context": "dtmi:dtdl:context;3",
        "@id": "dtmi:example:zatz_iota;1",
        "@type": "Interface",
        "schemas": {
          "@id": "dtmi:foo:bar;999999999",
          "@type": "Enum",
          "valueSchema": "integer"
        }
      }
    ]
  },
  {
    "valid": true,
    "options": [
      "DisallowUndefinedExtensions"
    ],
    "input": [
      {
        "@context": "dtmi:dtdl:context;3",
        "@id": "dtmi:example:zatz_kappa;1",
        "@type": "Interface",
        "schemas": {
          "@id": "dtmi:foo;1",
          "@type": "Enum",
          "valueSchema": "integer"
        }
      }
    ]
  },
  {
    "valid": true,
    "options": [
      "DisallowUndefinedExtensions"
    ],
    "input": [
      {
        "@context": "dtmi:dtdl:context;3",
        "@id": "dtmi:example:zatz_lambda;1",
        "@type": "Interface",
        "schemas": {
          "@id": "dtmi:foo:bar",
          "@type": "Enum",
          "valueSchema": "integer"
        }
      }
    ]
  },
  {
    "valid": true,
    "options": [
      "DisallowUndefinedExtensions"
    ],
    "input": [
      {
        "@context": "dtmi:dtdl:context;3",
        "@id": "dtmi:example:zatz_mu;1",
        "@type": "Interface",
        "schemas": {
          "@id": "dtmi:foo:bar;3.14",
          "@type": "Enum",
          "valueSchema": "integer"
        }
      }
    ]
  },
  {
    "valid": true,
    "options": [
      "DisallowUndefinedExtensions"
    ],
    "input": [
      {
        "@context": "dtmi:dtdl:context;3",
        "@id": "dtmi:example:zatz_nu;1",
        "@type": "Interface",
        "schemas": {
          "@id": "dtmi:foo:bar;3.141592",
          "@type": "Enum",
          "valueSchema": "integer"
        }
      }
    ]
  },
  {
    "valid": false,
    "options": [
      "DisallowUndefinedExtensions"
    ],
    "input": [
      {
        "@context": "dtmi:dtdl:context;3",
        "@id": "dtmi:example:zatz_xi;1",
        "@type": "Interface",
        "schemas": {
          "@id": null,
          "@type": "Enum",
          "valueSchema": "integer"
        }
      }
    ]
  },
  {
    "valid": false,
    "options": [
      "AllowUndefinedExtensions"
    ],
    "input": [
      {
        "@context": "dtmi:dtdl:context;3",
        "@id": "dtmi:example:zatz_omicron;1",
        "@type": "Interface",
        "schemas": {
          "@context": "dtmi:undefinedExtension:context;1",
          "@id": null,
          "@type": "Enum",
          "valueSchema": "integer"
        }
      }
    ]
  },
  {
    "valid": false,
    "options": [
      "DisallowUndefinedExtensions"
    ],
    "input": [
      {
        "@context": "dtmi:dtdl:context;3",
        "@id": "dtmi:example:zatz_pi;1",
        "@type": "Interface",
        "schemas": {
          "@id": 626,
          "@type": "Enum",
          "valueSchema": "integer"
        }
      }
    ]
  },
  {
    "valid": false,
    "options": [
      "AllowUndefinedExtensions"
    ],
    "input": [
      {
        "@context": "dtmi:dtdl:context;3",
        "@id": "dtmi:example:zatz_rho;1",
        "@type": "Interface",
        "schemas": {
          "@context": "dtmi:undefinedExtension:context;1",
          "@id": 626,
          "@type": "Enum",
          "valueSchema": "integer"
        }
      }
    ]
  },
  {
    "valid": false,
    "options": [
      "DisallowUndefinedExtensions"
    ],
    "input": [
      {
        "@context": "dtmi:dtdl:context;3",
        "@id": "dtmi:example:zatz_sigma;1",
        "@type": "Interface",
        "schemas": {
          "@id": true,
          "@type": "Enum",
          "valueSchema": "integer"
        }
      }
    ]
  },
  {
    "valid": false,
    "options": [
      "AllowUndefinedExtensions"
    ],
    "input": [
      {
        "@context": "dtmi:dtdl:context;3",
        "@id": "dtmi:example:zatz_tau;1",
        "@type": "Interface",
        "schemas": {
          "@context": "dtmi:undefinedExtension:context;1",
          "@id": true,
          "@type": "Enum",
          "valueSchema": "integer"
        }
      }
    ]
  },
  {
    "valid": false,
    "options": [
      "DisallowUndefinedExtensions"
    ],
    "input": [
      {
        "@context": "dtmi:dtdl:context;3",
        "@id": "dtmi:example:zatz_upsilon;1",
        "@type": "Interface",
        "schemas": {
          "@id": {
            "@value": "dtmi:apparently:valid:identifier;3"
          },
          "@type": "Enum",
          "valueSchema": "integer"
        }
      }
    ]
  },
  {
    "valid": false,
    "options": [
      "AllowUndefinedExtensions"
    ],
    "input": [
      {
        "@context": "dtmi:dtdl:context;3",
        "@id": "dtmi:example:zatz_phi;1",
        "@type": "Interface",
        "schemas": {
          "@context": "dtmi:undefinedExtension:context;1",
          "@id": {
            "@value": "dtmi:apparently:valid:identifier;3"
          },
          "@type": "Enum",
          "valueSchema": "integer"
        }
      }
    ]
  },
  {
    "valid": false,
    "options": [
      "DisallowUndefinedExtensions"
    ],
    "input": [
      {
        "@context": "dtmi:dtdl:context;3",
        "@id": "dtmi:example:zatz_chi;1",
        "@type": "Interface",
        "schemas": {
          "@id": "dtmi:foo:bar;0",
          "@type": "Enum",
          "valueSchema": "integer"
        }
      }
    ]
  },
  {
    "valid": false,
    "options": [
      "AllowUndefinedExtensions"
    ],
    "input": [
      {
        "@context": "dtmi:dtdl:context;3",
        "@id": "dtmi:example:zatz_psi;1",
        "@type": "Interface",
        "schemas": {
          "@context": "dtmi:undefinedExtension:context;1",
          "@id": "dtmi:foo:bar;0",
          "@type": "Enum",
          "valueSchema": "integer"
        }
      }
    ]
  },
  {
    "valid": false,
    "options": [
      "DisallowUndefinedExtensions"
    ],
    "input": [
      {
        "@context": "dtmi:dtdl:context;3",
        "@id": "dtmi:example:zatz_omega;1",
        "@type": "Interface",
        "schemas": {
          "@id": "dtmi:foo:bar;0.0",
          "@type": "Enum",
          "valueSchema": "integer"
        }
      }
    ]
  },
  {
    "valid": false,
    "options": [
      "AllowUndefinedExtensions"
    ],
    "input": [
      {
        "@context": "dtmi:dtdl:context;3",
        "@id": "dtmi:example:zatz_yuzz;1",
        "@type": "Interface",
        "schemas": {
          "@context": "dtmi:undefinedExtension:context;1",
          "@id": "dtmi:foo:bar;0.0",
          "@type": "Enum",
          "valueSchema": "integer"
        }
      }
    ]
  },
  {
    "valid": false,
    "options": [
      "DisallowUndefinedExtensions"
    ],
    "input": [
      {
        "@context": "dtmi:dtdl:context;3",
        "@id": "dtmi:example:zatz_wum;1",
        "@type": "Interface",
        "schemas": {
          "@id": "dtmi:foo:bar;1234567890",
          "@type": "Enum",
          "valueSchema": "integer"
        }
      }
    ]
  },
  {
    "valid": false,
    "options": [
      "AllowUndefinedExtensions"
    ],
    "input": [
      {
        "@context": "dtmi:dtdl:context;3",
        "@id": "dtmi:example:zatz_um;1",
        "@type": "Interface",
        "schemas": {
          "@context": "dtmi:undefinedExtension:context;1",
          "@id": "dtmi:foo:bar;1234567890",
          "@type": "Enum",
          "valueSchema": "integer"
        }
      }
    ]
  },
  {
    "valid": false,
    "options": [
      "DisallowUndefinedExtensions"
    ],
    "input": [
      {
        "@context": "dtmi:dtdl:context;3",
        "@id": "dtmi:example:zatz_humpf;1",
        "@type": "Interface",
        "schemas": {
          "@id": "dtmi:foo:bar;1a",
          "@type": "Enum",
          "valueSchema": "integer"
        }
      }
    ]
  },
  {
    "valid": false,
    "options": [
      "AllowUndefinedExtensions"
    ],
    "input": [
      {
        "@context": "dtmi:dtdl:context;3",
        "@id": "dtmi:example:zatz_fuddle;1",
        "@type": "Interface",
        "schemas": {
          "@context": "dtmi:undefinedExtension:context;1",
          "@id": "dtmi:foo:bar;1a",
          "@type": "Enum",
          "valueSchema": "integer"
        }
      }
    ]
  },
  {
    "valid": false,
    "options": [
      "DisallowUndefinedExtensions"
    ],
    "input": [
      {
        "@context": "dtmi:dtdl:context;3",
        "@id": "dtmi:example:zatz_glikk;1",
        "@type": "Interface",
        "schemas": {
          "@id": "dtmi:foo:bar;3.0",
          "@type": "Enum",
          "valueSchema": "integer"
        }
      }
    ]
  },
  {
    "valid": false,
    "options": [
      "AllowUndefinedExtensions"
    ],
    "input": [
      {
        "@context": "dtmi:dtdl:context;3",
        "@id": "dtmi:example:zatz_nuh;1",
        "@type": "Interface",
        "schemas": {
          "@context": "dtmi:undefinedExtension:context;1",
          "@id": "dtmi:foo:bar;3.0",
          "@type": "Enum",
          "valueSchema": "integer"
        }
      }
    ]
  },
  {
    "valid": false,
    "options": [
      "DisallowUndefinedExtensions"
    ],
    "input": [
      {
        "@context": "dtmi:dtdl:context;3",
        "@id": "dtmi:example:zatz_snee;1",
        "@type": "Interface",
        "schemas": {
          "@id": "dtmi:foo:bar;3.1415926",
          "@type": "Enum",
          "valueSchema": "integer"
        }
      }
    ]
  },
  {
    "valid": false,
    "options": [
      "AllowUndefinedExtensions"
    ],
    "input": [
      {
        "@context": "dtmi:dtdl:context;3",
        "@id": "dtmi:example:zatz_quan;1",
        "@type": "Interface",
        "schemas": {
          "@context": "dtmi:undefinedExtension:context;1",
          "@id": "dtmi:foo:bar;3.1415926",
          "@type": "Enum",
          "valueSchema": "integer"
        }
      }
    ]
  },
  {
    "valid": false,
    "options": [
      "DisallowUndefinedExtensions"
    ],
    "input": [
      {
        "@context": "dtmi:dtdl:context;3",
        "@id": "dtmi:example:zatz_thnad;1",
        "@type": "Interface",
        "schemas": {
          "@id": "dtmi:foo:bar;6.02",
          "@type": "Enum",
          "valueSchema": "integer"
        }
      }
    ]
  },
  {
    "valid": false,
    "options": [
      "AllowUndefinedExtensions"
    ],
    "input": [
      {
        "@context": "dtmi:dtdl:context;3",
        "@id": "dtmi:example:zatz_spazz;1",
        "@type": "Interface",
        "schemas": {
          "@context": "dtmi:undefinedExtension:context;1",
          "@id": "dtmi:foo:bar;6.02",
          "@type": "Enum",
          "valueSchema": "integer"
        }
      }
    ]
  },
  {
    "valid": false,
    "options": [
      "DisallowUndefinedExtensions"
    ],
    "input": [
      {
        "@context": "dtmi:dtdl:context;3",
        "@id": "dtmi:example:zatz_floob;1",
        "@type": "Interface",
        "schemas": {
          "@id": "dtmi:foo:bar;0.1",
          "@type": "Enum",
          "valueSchema": "integer"
        }
      }
    ]
  },
  {
    "valid": false,
    "options": [
      "AllowUndefinedExtensions"
    ],
    "input": [
      {
        "@context": "dtmi:dtdl:context;3",
        "@id": "dtmi:example:zatz_zatz;1",
        "@type": "Interface",
        "schemas": {
          "@context": "dtmi:undefinedExtension:context;1",
          "@id": "dtmi:foo:bar;0.1",
          "@type": "Enum",
          "valueSchema": "integer"
        }
      }
    ]
  },
  {
    "valid": false,
    "options": [
      "DisallowUndefinedExtensions"
    ],
    "input": [
      {
        "@context": "dtmi:dtdl:context;3",
        "@id": "dtmi:example:zatz_jogg;1",
        "@type": "Interface",
        "schemas": {
          "@id": "dtmi:foo:bar;01",
          "@type": "Enum",
          "valueSchema": "integer"
        }
      }
    ]
  },
  {
    "valid": false,
    "options": [
      "AllowUndefinedExtensions"
    ],
    "input": [
      {
        "@context": "dtmi:dtdl:context;3",
        "@id": "dtmi:example:zatz_flunn;1",
        "@type": "Interface",
        "schemas": {
          "@context": "dtmi:undefinedExtension:context;1",
          "@id": "dtmi:foo:bar;01",
          "@type": "Enum",
          "valueSchema": "integer"
        }
      }
    ]
  },
  {
    "valid": false,
    "options": [
      "DisallowUndefinedExtensions"
    ],
    "input": [
      {
        "@context": "dtmi:dtdl:context;3",
        "@id": "dtmi:example:zatz_itch;1",
        "@type": "Interface",
        "schemas": {
          "@id": "dtmi:foo:bar;",
          "@type": "Enum",
          "valueSchema": "integer"
        }
      }
    ]
  },
  {
    "valid": false,
    "options": [
      "AllowUndefinedExtensions"
    ],
    "input": [
      {
        "@context": "dtmi:dtdl:context;3",
        "@id": "dtmi:example:zatz_yekk;1",
        "@type": "Interface",
        "schemas": {
          "@context": "dtmi:undefinedExtension:context;1",
          "@id": "dtmi:foo:bar;",
          "@type": "Enum",
          "valueSchema": "integer"
        }
      }
    ]
  },
  {
    "valid": false,
    "options": [
      "DisallowUndefinedExtensions"
    ],
    "input": [
      {
        "@context": "dtmi:dtdl:context;3",
        "@id": "dtmi:example:zatz_vroo;1",
        "@type": "Interface",
        "schemas": {
          "@id": "dtmi:test:invalidId_;1",
          "@type": "Enum",
          "valueSchema": "integer"
        }
      }
    ]
  },
  {
    "valid": false,
    "options": [
      "AllowUndefinedExtensions"
    ],
    "input": [
      {
        "@context": "dtmi:dtdl:context;3",
        "@id": "dtmi:example:zatz_hi;1",
        "@type": "Interface",
        "schemas": {
          "@context": "dtmi:undefinedExtension:context;1",
          "@id": "dtmi:test:invalidId_;1",
          "@type": "Enum",
          "valueSchema": "integer"
        }
      }
    ]
  },
  {
    "valid": false,
    "options": [
      "DisallowUndefinedExtensions"
    ],
    "input": [
      {
        "@context": "dtmi:dtdl:context;3",
        "@id": "dtmi:example:jogg_alpha;1",
        "@type": "Interface",
        "schemas": {
          "@id": "dtmi:test:_invalidUserId;1",
          "@type": "Enum",
          "valueSchema": "integer"
        }
      }
    ]
  },
  {
    "valid": false,
    "options": [
      "AllowUndefinedExtensions"
    ],
    "input": [
      {
        "@context": "dtmi:dtdl:context;3",
        "@id": "dtmi:example:jogg_beta;1",
        "@type": "Interface",
        "schemas": {
          "@context": "dtmi:undefinedExtension:context;1",
          "@id": "dtmi:test:_invalidUserId;1",
          "@type": "Enum",
          "valueSchema": "integer"
        }
      }
    ]
  },
  {
    "valid": false,
    "options": [
      "DisallowUndefinedExtensions"
    ],
    "input": [
      {
        "@context": "dtmi:dtdl:context;3",
        "@id": "dtmi:example:jogg_gamma;1",
        "@type": "Interface",
        "schemas": {
          "@id": "dtmi:test:1seg;1",
          "@type": "Enum",
          "valueSchema": "integer"
        }
      }
    ]
  },
  {
    "valid": false,
    "options": [
      "AllowUndefinedExtensions"
    ],
    "input": [
      {
        "@context": "dtmi:dtdl:context;3",
        "@id": "dtmi:example:jogg_delta;1",
        "@type": "Interface",
        "schemas": {
          "@context": "dtmi:undefinedExtension:context;1",
          "@id": "dtmi:test:1seg;1",
          "@type": "Enum",
          "valueSchema": "integer"
        }
      }
    ]
  },
  {
    "valid": false,
    "options": [
      "DisallowUndefinedExtensions"
    ],
    "input": [
      {
        "@context": "dtmi:dtdl:context;3",
        "@id": "dtmi:example:jogg_epsilon;1",
        "@type": "Interface",
        "schemas": {
          "@id": "dtmi:foo:bar.baz;1",
          "@type": "Enum",
          "valueSchema": "integer"
        }
      }
    ]
  },
  {
    "valid": false,
    "options": [
      "AllowUndefinedExtensions"
    ],
    "input": [
      {
        "@context": "dtmi:dtdl:context;3",
        "@id": "dtmi:example:jogg_zeta;1",
        "@type": "Interface",
        "schemas": {
          "@context": "dtmi:undefinedExtension:context;1",
          "@id": "dtmi:foo:bar.baz;1",
          "@type": "Enum",
          "valueSchema": "integer"
        }
      }
    ]
  },
  {
    "valid": false,
    "options": [
      "DisallowUndefinedExtensions"
    ],
    "input": [
      {
        "@context": "dtmi:dtdl:context;3",
        "@id": "dtmi:example:jogg_eta;1",
        "@type": "Interface",
        "schemas": {
          "@id": "dtmi:foo::bar;1",
          "@type": "Enum",
          "valueSchema": "integer"
        }
      }
    ]
  },
  {
    "valid": false,
    "options": [
      "AllowUndefinedExtensions"
    ],
    "input": [
      {
        "@context": "dtmi:dtdl:context;3",
        "@id": "dtmi:example:jogg_theta;1",
        "@type": "Interface",
        "schemas": {
          "@context": "dtmi:undefinedExtension:context;1",
          "@id": "dtmi:foo::bar;1",
          "@type": "Enum",
          "valueSchema": "integer"
        }
      }
    ]
  },
  {
    "valid": false,
    "options": [
      "DisallowUndefinedExtensions"
    ],
    "input": [
      {
        "@context": "dtmi:dtdl:context;3",
        "@id": "dtmi:example:jogg_iota;1",
        "@type": "Interface",
        "schemas": {
          "@id": "urn:foo:bar:1",
          "@type": "Enum",
          "valueSchema": "integer"
        }
      }
    ]
  },
  {
    "valid": false,
    "options": [
      "AllowUndefinedExtensions"
    ],
    "input": [
      {
        "@context": "dtmi:dtdl:context;3",
        "@id": "dtmi:example:jogg_kappa;1",
        "@type": "Interface",
        "schemas": {
          "@context": "dtmi:undefinedExtension:context;1",
          "@id": "urn:foo:bar:1",
          "@type": "Enum",
          "valueSchema": "integer"
        }
      }
    ]
  },
  {
    "valid": false,
    "options": [
      "DisallowUndefinedExtensions"
    ],
    "input": [
      {
        "@context": "dtmi:dtdl:context;3",
        "@id": "dtmi:example:jogg_lambda;1",
        "@type": "Interface",
        "schemas": {
          "@id": "http://foo/bar/baz",
          "@type": "Enum",
          "valueSchema": "integer"
        }
      }
    ]
  },
  {
    "valid": false,
    "options": [
      "AllowUndefinedExtensions"
    ],
    "input": [
      {
        "@context": "dtmi:dtdl:context;3",
        "@id": "dtmi:example:jogg_mu;1",
        "@type": "Interface",
        "schemas": {
          "@context": "dtmi:undefinedExtension:context;1",
          "@id": "http://foo/bar/baz",
          "@type": "Enum",
          "valueSchema": "integer"
        }
      }
    ]
  },
  {
    "valid": false,
    "options": [
      "DisallowUndefinedExtensions"
    ],
    "input": [
      {
        "@context": "dtmi:dtdl:context;3",
        "@id": "dtmi:example:jogg_nu;1",
        "@type": "Interface",
        "schemas": {
          "@id": "dtmi:;1",
          "@type": "Enum",
          "valueSchema": "integer"
        }
      }
    ]
  },
  {
    "valid": false,
    "options": [
      "AllowUndefinedExtensions"
    ],
    "input": [
      {
        "@context": "dtmi:dtdl:context;3",
        "@id": "dtmi:example:jogg_xi;1",
        "@type": "Interface",
        "schemas": {
          "@context": "dtmi:undefinedExtension:context;1",
          "@id": "dtmi:;1",
          "@type": "Enum",
          "valueSchema": "integer"
        }
      }
    ]
  },
  {
    "valid": false,
    "options": [
      "DisallowUndefinedExtensions"
    ],
    "input": [
      {
        "@context": "dtmi:dtdl:context;3",
        "@id": "dtmi:example:jogg_omicron;1",
        "@type": "Interface",
        "schemas": {
          "@id": "dtmi:dtdl:example;1",
          "@type": "Enum",
          "valueSchema": "integer"
        }
      }
    ]
  },
  {
    "valid": false,
    "options": [
      "AllowUndefinedExtensions"
    ],
    "input": [
      {
        "@context": "dtmi:dtdl:context;3",
        "@id": "dtmi:example:jogg_pi;1",
        "@type": "Interface",
        "schemas": {
          "@context": "dtmi:undefinedExtension:context;1",
          "@id": "dtmi:dtdl:example;1",
          "@type": "Enum",
          "valueSchema": "integer"
        }
      }
    ]
  },
  {
    "valid": false,
    "options": [
      "DisallowUndefinedExtensions"
    ],
    "input": [
      {
        "@context": "dtmi:dtdl:context;3",
        "@id": "dtmi:example:jogg_rho;1",
        "@type": "Interface",
        "schemas": {
          "@id": "dtmi:standard:example;1",
          "@type": "Enum",
          "valueSchema": "integer"
        }
      }
    ]
  },
  {
    "valid": false,
    "options": [
      "AllowUndefinedExtensions"
    ],
    "input": [
      {
        "@context": "dtmi:dtdl:context;3",
        "@id": "dtmi:example:jogg_sigma;1",
        "@type": "Interface",
        "schemas": {
          "@context": "dtmi:undefinedExtension:context;1",
          "@id": "dtmi:standard:example;1",
          "@type": "Enum",
          "valueSchema": "integer"
        }
      }
    ]
  }
]
