[
  {
    "valid": true,
    "options": [
      "DisallowUndefinedExtensions"
    ],
    "input": [
      {
        "@context": "dtmi:dtdl:context;2",
        "@id": "dtmi:example:thnad_glikk;1",
        "@type": "Interface",
        "schemas": {
          "@id": "dtmi:example:thnad_wum;1",
          "@type": "Map",
          "dtmi:dtdl:property:description;2": [
            "thnad_um"
          ],
          "mapKey": {
            "name": "thnad_humpf",
            "schema": "string"
          },
          "mapValue": {
            "name": "thnad_fuddle",
            "schema": "double"
          }
        }
      }
    ]
  }
]
