[
  {
    "valid": false,
    "options": [
      "DisallowUndefinedExtensions"
    ],
    "input": [
      {
        "@context": "dtmi:dtdl:context;2",
        "@id": "dtmi:example:upsilon_chi;1",
        "@type": "Interface",
        "contents": {
          "@type": [
            "Command",
            "dtmi:foo:bar;1"
          ],
          "name": "upsilon_phi"
        }
      }
    ]
  },
  {
    "valid": true,
    "options": [
      "AllowUndefinedExtensions"
    ],
    "input": [
      {
        "@context": "dtmi:dtdl:context;2",
        "@id": "dtmi:example:upsilon_omega;1",
        "@type": "Interface",
        "contents": {
          "@context": "dtmi:undefinedExtension:context;1",
          "@type": [
            "Command",
            "dtmi:foo:bar;1"
          ],
          "name": "upsilon_psi"
        }
      }
    ]
  },
  {
    "valid": false,
    "options": [
      "DisallowUndefinedExtensions"
    ],
    "input": [
      {
        "@context": "dtmi:dtdl:context;2",
        "@id": "dtmi:example:upsilon_wum;1",
        "@type": "Interface",
        "contents": {
          "@type": [
            "Command",
            "boolean"
          ],
          "name": "upsilon_yuzz"
        }
      }
    ]
  },
  {
    "valid": true,
    "options": [
      "AllowUndefinedExtensions"
    ],
    "input": [
      {
        "@context": "dtmi:dtdl:context;2",
        "@id": "dtmi:example:upsilon_humpf;1",
        "@type": "Interface",
        "contents": {
          "@context": "dtmi:undefinedExtension:context;1",
          "@type": [
            "Command",
            "boolean"
          ],
          "name": "upsilon_um"
        }
      }
    ]
  }
]
